{"packages/cupertino_icons/assets/CupertinoIcons.ttf":["packages/cupertino_icons/assets/CupertinoIcons.ttf"],"assets/images/backboard_d1550.png":["assets/images/backboard_d1550.png"],"assets/images/background_d1536.png":["assets/images/background_d1536.png"],"assets/images/frontboard_d1550.png":["assets/images/frontboard_d1550.png"],"assets/images/pionjaune1_d200.png":["assets/images/pionjaune1_d200.png"],"assets/images/pionjaune2_d200.png":["assets/images/pionjaune2_d200.png"],"assets/images/pionjaune3_d200.png":["assets/images/pionjaune3_d200.png"],"assets/images/pionjaune4_d200.png":["assets/images/pionjaune4_d200.png"],"assets/images/pionred1_d200.png":["assets/images/pionred1_d200.png"],"assets/images/pionred2_d200.png":["assets/images/pionred2_d200.png"],"assets/images/pionred3_d200.png":["assets/images/pionred3_d200.png"],"assets/images/pionred4_d200.png":["assets/images/pionred4_d200.png"],"assets/images/scorebar_d640.png":["assets/images/scorebar_d640.png"]}